{
  "id": 108,
  "slug": "clair-obscur-expedition-33",
  "playerExp": {
    "media": {
      "memory": [
        {
          "text": "<b>手绘美术+虚幻5写实</b>的混搭风格前所未见——角色和环境同时具备油画笔触和照片级光影",
          "src": "IGN 9分"
        },
        {
          "text": "<b>即时操作+回合策略</b>的融合战斗系统——弹反/闪避是实时操作，指令是策略回合，两种快感并存",
          "src": "GameSpot 9分"
        },
        {
          "text": "<b>法式诗意叙事</b>——不同于日式和美式RPG的调性，有种独特的文艺气质",
          "src": "Eurogamer"
        }
      ],
      "excitement": [
        {
          "text": "<b>Metacritic 88+ 分</b>——2025 年上半年评分最高的新 IP RPG",
          "src": "Metacritic"
        },
        {
          "text": "来自<b>法国 20 人小团队</b>的首部作品就达到 3A 品质——独立开发奇迹",
          "src": "Game Informer"
        },
        {
          "text": "<b>Boss 设计</b>极具创意——每个 Boss 都像一件当代艺术装置",
          "src": "Polygon"
        }
      ],
      "pain": [
        {
          "text": "部分<b>回合制战斗节奏</b>偏慢——尤其在小怪遭遇战中操作重复",
          "src": "多媒体综合"
        },
        {
          "text": "<b>叙事风格</b>偏抽象诗意——喜欢直白故事的玩家可能不适应",
          "src": "GameSpot"
        }
      ],
      "churn": [
        {
          "text": "部分<b>解谜环节</b>提示不足——容易卡关导致放弃",
          "src": "Steam 评论"
        },
        {
          "text": "非回合制 RPG 爱好者可能被<b>战斗系统的学习曲线</b>劝退",
          "src": "多平台综合"
        }
      ]
    },
    "community": {
      "memory": [
        {
          "text": "「<b>2025 年最大惊喜</b>」——社区没想到一个法国小团队能做出这个水准的 RPG",
          "src": "Reddit / ResetEra"
        },
        {
          "text": "<b>美术风格</b>成为设计圈热议话题——被称为「最像油画的游戏」",
          "src": "Dribbble / 设计师社区"
        }
      ],
      "excitement": [
        {
          "text": "<b>Game Pass 首日</b>+口碑爆发形成完美组合——大量玩家零成本入坑",
          "src": "Xbox / Steam"
        },
        {
          "text": "社区对<b>Boss 设计</b>的讨论热度极高——每个 Boss 的艺术分析成为热帖",
          "src": "Reddit"
        }
      ],
      "pain": [
        {
          "text": "部分平台<b>技术问题</b>——Xbox 版帧率不稳、偶有闪退",
          "src": "Xbox 社区"
        },
        {
          "text": "<b>中文本地化</b>质量一般——部分翻译不够准确",
          "src": "NGA"
        }
      ],
      "churn": [
        {
          "text": "<b>后期难度曲线</b>陡升——部分 Boss 需要反复尝试",
          "src": "Steam 评论"
        },
        {
          "text": "偏<b>线性的流程</b>和有限的探索空间限制了自由度",
          "src": "多平台综合"
        }
      ]
    },
    "biliVideos": [
      {
        "title": "光暗交响 全流程实况 4K",
        "bvid": "BV1kS4y1K7pN",
        "views": "280万"
      },
      {
        "title": "2025年最美RPG！Clair Obscur 深度评测",
        "bvid": "BV1wm42197kQ",
        "views": "350万"
      },
      {
        "title": "光暗交响 全Boss战合集 无伤",
        "bvid": "BV1fz421B7hK",
        "views": "190万"
      },
      {
        "title": "Clair Obscur 美术解析——油画般的游戏世界",
        "bvid": "BV1Nm421E7kS",
        "views": "240万"
      },
      {
        "title": "法国小团队如何做出3A品质RPG",
        "bvid": "BV1rz4y1R7mQ",
        "views": "160万"
      }
    ]
  },
  "aesthetic": {
    "scene": {
      "title": "法式印象派 x UE5 照片级 - 油画笔触与光追共存",
      "value": "场景视觉是本作最大标签——所有环境在<b>UE5 照片级渲染</b>基础上叠加<b>印象派油画笔触后处理</b>，形成独一无二的「可行走油画」效果；色调随区域大幅变化：<b>海岸蓝白</b>（地中海日光感）、<b>森林暖绿</b>（莫奈花园质感）、<b>废墟灰紫</b>（浪漫主义废墟美学）；光影是核心表现力——<b>丁达尔效应</b>、体积雾、散射光被大量使用，让每个角落都像印象派画作"
    },
    "costume": {
      "title": "法式Belle Époque x 暗黑奇幻 - 优雅与战斗的混搭",
      "value": "角色服装设计融合<b>19世纪法国美好时代</b>的优雅裁剪与暗黑奇幻的战斗功能——长外套、高领、流苏、金属扣的混搭；主角团穿着有<b>军装骑行服</b>质感的冒险装——结构硬朗但不失优雅；Boss 造型走<b>当代艺术装置</b>路线——巨大、抽象、令人不安的美感，像 Alexander McQueen 的高定秀场"
    },
    "ui": {
      "title": "手绘风格化 - 墨水线条 x 复古版画质感",
      "value": "战斗 UI 使用<b>手绘墨水线条</b>框架——技能图标有版画雕刻质感；HP/MP 条用<b>水彩渐变</b>填充而非纯色；菜单界面用<b>旧书页纹理+手写字体</b>营造复古感；战斗中的即时操作提示用简洁几何图形，不干扰视觉沉浸；整体 UI 设计理念：<b>让界面成为美术风格的延伸，而非独立于画面之外</b>"
    },
    "symbol": {
      "title": "数字33 x 倒计时沙漏 x 画笔与颜料 x 光与暗",
      "value": "核心视觉符号：<b>数字 33</b>（远征代号，贯穿全程的宿命标记）、<b>光与暗的对比</b>（标题即母题——Clair/明与Obscur/暗的永恒对抗）、<b>油画笔触</b>（世界本身就像一幅未完成的画——边缘模糊、色块流淌）；色彩母题为<b>蓝白+暖金+深紫</b>的法式配色——既优雅又忧郁"
    },
    "promo": {
      "title": "黑马出圈 - 视觉即卖点，独立精神即品牌",
      "value": "宣发核心是<b>「见所未见的 RPG 视觉」</b>——首支预告片凭借独特的油画质感瞬间出圈，截图疯传；Key Art 使用<b>主角团行走在画布般大地上</b>的构图，强调「行走的油画」概念；作为<b>Game Pass 首日游戏</b>大幅降低了入门门槛，口碑裂变迅速；品牌叙事打<b>「法国小团队的3A梦想」</b>牌，独立精神引发玩家共鸣"
    },
    "rivals": [
      {
        "id": 105,
        "reason": "同为回合制RPG+高度风格化美术——Atlus式平面vs法式油画的风格化路线对标"
      },
      {
        "id": 104,
        "reason": "同为高投入RPG——即时指令vs回合操作融合的战斗UI设计对比"
      },
      {
        "id": 102,
        "reason": "同为UE5高品质大作——写实暗黑 vs 油画诗意的美学取向对比"
      },
      {
        "id": 101,
        "reason": "同为高评分RPG新作——中国水墨vs法式油画的东西方风格化差异"
      }
    ]
  },
  "story": {
    "title": "世界观与叙事",
    "dims": [
      {
        "label": "时间",
        "value": "<b>架空 Belle Époque 时代</b>——类似 19 世纪末法国美好年代的文明水平+超自然魔法"
      },
      {
        "label": "发生地",
        "value": "<b>被画匠诅咒的大陆</b>——一个被神秘「画匠」（Paintress）每年抹去一个年龄段人口的世界"
      },
      {
        "label": "角色扮演什么",
        "value": "「<b>第 33 远征队</b>」——对抗画匠诅咒的勇士小队，每个成员都是即将被抹去的年龄段中选出的志愿者"
      },
      {
        "label": "科技水平",
        "value": "<b>蒸汽时代+魔法</b>——火车、蒸汽动力机械与魔法超能力并存，有轻微蒸汽朋克元素"
      },
      {
        "label": "对抗关系",
        "value": "<b>远征队 vs 画匠 (Paintress) 的守护者</b>——画匠是超越性的存在（巨大、抽象、艺术装置般的视觉），守护者各有独特的艺术主题外观"
      },
      {
        "label": "地图",
        "value": "<b>半开放探索</b>：法式小镇据点 → 自然荒野/废墟探索 → Boss 领域挑战；风格从地中海海岸到暗色密林不等"
      },
      {
        "label": "元素",
        "value": "<b>法式诗意 × 印象派视觉 × 存在主义叙事</b>；视觉标识为「可行走的油画」——环境和角色共享同一套笔触语言；受莫奈/雷诺阿印象派画风、法国文学（加缪/圣埃克苏佩里）、当代艺术装置启发"
      }
    ]
  }
}