{
  "id": 234,
  "slug": "genshin-impact",
  "playerExp": {
    "media": {
      "memory": [
        {
          "text": "提瓦特大陆\"每一处都塞满了5个以上可发现要素\"——跟随一只蓝色精灵可能触发战斗、宝箱、解谜或隐藏 Boss，这种<b>链式探索涌现</b>在开放世界设计中达到了密度的极致",
          "src": "IGN",
          "url": "https://www.ign.com/articles/genshin-impact-review"
        },
        {
          "text": "<b>元素反应系统</b>将传统属性克制提升到全新高度——水附着+雷攻击=感电扩散、冰冻+火=蒸发倍率伤害，4人队伍的元素链式反应让每场战斗都是化学实验",
          "src": "IGN",
          "url": "https://www.ign.com/articles/genshin-impact-review"
        },
        {
          "text": "首年移动端收入突破<b>20亿美元</b>、2021年 Twitter 讨论度最高游戏——原神证明了<b>免费制开放世界</b>动作RPG可以同时在品质和商业上达到3A顶级水准",
          "src": "Eurogamer",
          "url": "https://www.eurogamer.net/genshin-impact-an-anime-open-world-not-done-with-expanding"
        }
      ],
      "excitement": [
        {
          "text": "在<b>闪电连续切人</b>中打出元素反应链的爽快感——行秋挂水、菲谢尔召奥兹感电、温迪聚怪扩散、迪卢克蒸发收割，4秒内完成的操作比大部分动作游戏一整场Boss战更有策略深度",
          "src": "IGN",
          "url": "https://www.ign.com/articles/genshin-impact-review"
        },
        {
          "text": "解锁新角色后发现它打开了<b>之前无法到达的探索路径</b>——冰角色冻结水面、风角色升起气流、岩角色搭建平台，角色收集与地图探索形成正向驱动闭环",
          "src": "IGN",
          "url": "https://www.ign.com/articles/genshin-impact-review"
        },
        {
          "text": "每个新国度上线时的<b>音乐与美术飞跃</b>——从蒙德的欧洲管弦到稻妻的日式太鼓再到须弥的中东弦乐，配乐团队为每个区域创作了完整的原创交响乐",
          "src": "Eurogamer",
          "url": "https://www.eurogamer.net/genshin-impact-an-anime-open-world-not-done-with-expanding"
        }
      ],
      "pain": [
        {
          "text": "<b>体力（树脂）系统</b>严格限制每日有效游玩时间——大部分材料获取需要消耗树脂，自然回复约需21小时才能充满，花钱也只能额外刷新有限次数",
          "src": "IGN",
          "url": "https://www.ign.com/articles/genshin-impact-review"
        },
        {
          "text": "五星角色<b>0.6%的基础出率</b>配合仅3周的限定卡池——要么忍受漫长的原石积攒，要么面对\"氪金还是放弃\"的尖锐抉择",
          "src": "IGN",
          "url": "https://www.ign.com/articles/genshin-impact-review"
        },
        {
          "text": "抽到角色后需要<b>大量材料投资</b>才能使其可用——等级突破、天赋书、周本材料、圣遗物的多层培养成本让新角色从获得到实战有数周的漫长养成期",
          "src": "IGN",
          "url": "https://www.ign.com/articles/genshin-impact-review"
        }
      ],
      "churn": [
        {
          "text": "<b>限时活动内容永久删除</b>是服务型游戏最大的设计争议——如金苹果群岛等包含重要角色故事的独占活动，错过后只能通过YouTube回顾，新玩家永远无法体验",
          "src": "Eurogamer",
          "url": "https://www.eurogamer.net/genshin-impact-an-anime-open-world-not-done-with-expanding"
        },
        {
          "text": "主线剧情<b>过多说明性对话</b>和套路化的动漫叙事——角色\"像按字数收费一样反复解释魔法术语\"，大量过场动画无法跳过，严重消耗玩家的叙事耐心",
          "src": "IGN",
          "url": "https://www.ign.com/articles/genshin-impact-review"
        },
        {
          "text": "后期进度的<b>指数级减速</b>——40-50小时后付费墙开始显现，高级内容中免费玩家的资源获取效率远低于氪金玩家，核心循环从\"探索发现\"退化为\"日常通勤\"",
          "src": "IGN",
          "url": "https://www.ign.com/articles/genshin-impact-review"
        }
      ]
    },
    "community": {
      "memory": [
        {
          "text": "\"第一次爬上龙脊雪山山顶、在暴风雪中看到整个提瓦特的全景时——<b>音乐骤然响起</b>的那一刻让我理解了什么叫'用风景讲故事'\"",
          "src": "Reddit r/Genshin_Impact",
          "url": "https://www.reddit.com/r/Genshin_Impact/"
        },
        {
          "text": "\"稻妻版本雷神巴尔 PV 公布时<b>全球同人爆发</b>——一个角色预告片就能让整个互联网沸腾，这是原神品牌力的终极体现\"",
          "src": "Reddit r/Genshin_Impact",
          "url": "https://www.reddit.com/r/Genshin_Impact/"
        }
      ],
      "excitement": [
        {
          "text": "\"研究圣遗物词条、精确计算<b>元素精通/暴击率</b>的最优配装方案——原神的养成深度堪比传统 MMO 的理论crafting，让数据党也能找到乐趣\"",
          "src": "Reddit r/Genshin_Impact",
          "url": "https://www.reddit.com/r/Genshin_Impact/"
        },
        {
          "text": "\"每次新版本上线探索<b>全新国度</b>时那种'回到第一天'的兴奋——须弥的雨林、枫丹的水下城市，每次都像在玩一款新游戏\"",
          "src": "Reddit r/Genshin_Impact",
          "url": "https://www.reddit.com/r/Genshin_Impact/"
        }
      ],
      "pain": [
        {
          "text": "\"<b>圣遗物刷取</b>是游戏最痛苦的体验——一个完美主词条圣遗物可能需要数月的每日刷本，RNG叠RNG的设计让人绝望\"",
          "src": "Reddit r/Genshin_Impact",
          "url": "https://www.reddit.com/r/Genshin_Impact/"
        },
        {
          "text": "\"花了全部积蓄抽角色结果<b>歪了/没出金</b>——保底机制虽然存在但180抽的硬保底意味着运气差的玩家需要积攒数月的资源\"",
          "src": "Reddit r/Genshin_Impact",
          "url": "https://www.reddit.com/r/Genshin_Impact/"
        }
      ],
      "churn": [
        {
          "text": "\"树脂花完之后<b>每天只能玩15分钟日常</b>——当一款游戏每天主动把你赶走，很多人真的就不回来了\"",
          "src": "Reddit r/Genshin_Impact",
          "url": "https://www.reddit.com/r/Genshin_Impact/"
        },
        {
          "text": "\"<b>崩坏星穹铁道/绝区零</b>出来之后原神的更新质量明显下滑——米哈游自家产品互相分流，老玩家转投新坑\"",
          "src": "Reddit r/Genshin_Impact",
          "url": "https://www.reddit.com/r/Genshin_Impact/"
        }
      ]
    },
    "biliVideos": []
  },
  "story": {
    "title": "旅行者穿越七国寻找失散的血亲",
    "dims": [
      {
        "label": "时间",
        "value": "提瓦特大陆的\"现世\"时代——<b>七神各据一方</b>、深渊教团暗中活动的史诗纪元，主线跨越旅行者寻找失散双胞胎的漫长旅途"
      },
      {
        "label": "发生地",
        "value": "提瓦特（Teyvat）——由<b>七个元素国度</b>构成的幻想大陆：蒙德（风/欧洲）、璃月（岩/中国）、稻妻（雷/日本）、须弥（草/中东南亚）、枫丹（水/法国）、纳塔（火/拉美）、冬极（冰/北欧俄罗斯）"
      },
      {
        "label": "角色扮演什么",
        "value": "<b>\"旅行者\"</b>——来自异世界的双胞胎之一，穿越七国<b>寻找被神秘力量分离的另一半</b>，同时卷入每个国家的元素神灵与人类的冲突"
      },
      {
        "label": "科技水平",
        "value": "<b>中世纪至蒸汽朋克的混合幻想科技</b>——每个国度根据对应元素发展出不同技术形态（璃月的仙术/枫丹的水利机械/须弥的学术体系），最先进的坎瑞亚文明因\"过度发展\"被神明摧毁"
      },
      {
        "label": "对抗关系",
        "value": "多层对抗——旅行者 vs 深渊教团、七国神明 vs <b>天理（Celestia 至高秩序）</b>、每个国家内部的政治矛盾；最终指向<b>世界秩序本身的正当性之争</b>"
      },
      {
        "label": "地图",
        "value": "<b>超大规模无缝开放世界</b>——7个主要国度+地下区域+海域，可攀爬/滑翔的垂直设计，持续通过版本更新扩展新区域"
      },
      {
        "label": "元素",
        "value": "<b>七元素系统</b>：风（Anemo）、岩（Geo）、雷（Electro）、草（Dendro）、水（Hydro）、火（Pyro）、冰（Cryo），元素之间的反应组合构成战斗和解谜的核心机制"
      }
    ]
  },
  "aesthetic": {
    "scene": {
      "title": "七国七色的动画风开放世界画卷",
      "value": "每个国度都是一次<b>完整的美术风格迭代</b>——蒙德的欧洲田园水彩、璃月的水墨山水仙侠、稻妻的浮世绘电闪雷鸣、须弥的热带雨林与沙漠对比、枫丹的新艺术运动水下都市。<b>赛璐璐渲染</b>+写实光影的混合技术让动画美术在开放世界体量下保持了一致的高品质表现力"
    },
    "costume": {
      "title": "角色设计即抽卡驱动力的视觉商业学",
      "value": "每个可玩角色都是精心计算的<b>视觉商品</b>——独特的配色方案确保<b>剪影辨识度</b>、元素标志性纹样融入服饰细节、性格通过穿着而非对话就能传达。五星角色的设计精度远超四星，用视觉落差驱动抽卡欲望。从雷电将军的和风铠甲到胡桃的中式冥府少女，每个角色都是一次文化视觉设计的命题作文"
    },
    "ui": {
      "title": "轻量化信息层的跨平台自适应界面",
      "value": "UI 需要同时服务 PC/主机/移动端三种场景——采用<b>白底+半透明毛玻璃</b>的统一视觉语言，图标以<b>元素色彩编码</b>（风=绿、火=红）确保快速识别。地图标记系统、任务追踪和角色切换轮盘在移动端的操作效率是核心设计挑战，通过激进的信息层级精简实现了可接受的触屏体验"
    },
    "symbol": {
      "title": "神之眼——元素力量的核心视觉锚点",
      "value": "<b>\"神之眼\"（Vision）</b>作为角色额头/腰间的宝石饰物是原神最强的符号设计——它同时是叙事道具（神的认可）、角色标识（元素属性一目了然）和玩家欲望投射（\"我也想拥有XXX的神之眼\"）。配合七元素的色彩体系和各国独特的神之眼外框设计，形成了一套跨文化的、可延展的核心视觉符号"
    },
    "promo": {
      "title": "角色PV+音乐会的二次元品牌运营范式",
      "value": "原神的宣发策略以<b>高品质角色 PV</b> 为核心引擎——每个新五星角色配备电影级预告片和专属BGM，<b>PV本身即内容产品</b>。年度音乐会直播将游戏配乐以交响乐团现场演出形式呈现，强化品质定位。持续的角色同人/Cosplay 生态和官方联动活动维持了\"活的\"品牌热度"
    },
    "rivals": [
      {
        "id": 235,
        "reason": "崩坏星穹铁道是<b>米哈游自家的内部分流竞品</b>——同一家公司用回合制RPG抢占自己开放世界动作RPG的用户时间和氪金预算"
      },
      {
        "id": 236,
        "reason": "绝区零是米哈游第三款产品，与原神争夺<b>二次元动作游戏</b>的同一批核心用户——从美术风格到角色营销都在同一赛道内竞争"
      },
      {
        "id": 237,
        "reason": "《燕云十六声》代表了<b>国产开放世界的另一条路径</b>——武侠题材 vs 二次元幻想，写实 vs 赛璐璐，但同样面对中国市场开放世界品类的用户争夺"
      },
      {
        "id": 102,
        "reason": "艾尔登法环与原神是<b>开放世界设计哲学的两极</b>——前者用减法（无标记/无引导）创造探索感，后者用加法（高密度标记/引导）维持探索驱动力"
      }
    ]
  }
}